namespacecraft/__init__.py
namespacecraft/namespace.py
namespacecraft/term.py
namespacecraft-0.3.2.dist-info/licenses/LICENCE
namespacecraft-0.3.2.dist-info/METADATA
namespacecraft-0.3.2.dist-info/WHEEL
namespacecraft-0.3.2.dist-info/top_level.txt
namespacecraft-0.3.2.dist-info/RECORD
