Metadata-Version: 2.4
Name: namespacecraft
Version: 0.3.2
Summary: Composable URI namespaces
Requires-Python: >=3.9
License-File: LICENCE
Dynamic: license-file
